gaps_dataset/__init__.py
gaps_dataset/ftp_info.py
gaps_dataset/ftp_utils.py
gaps_dataset/gaps.py
gaps_dataset/version.py
gaps_dataset/examples/__init__.py
gaps_dataset/examples/gaps10m_load_segmentation.py
gaps_dataset/examples/gapsV1_load_images.py
gaps_dataset/examples/gapsV1_load_patches.py
gaps_dataset/examples/gapsV2_load_images.py
gaps_dataset/examples/gapsV2_load_patches.py
gaps_dataset/examples/gapsV2_load_segmentation.py
gaps_dataset-3.0.0.dist-info/METADATA
gaps_dataset-3.0.0.dist-info/WHEEL
gaps_dataset-3.0.0.dist-info/top_level.txt
gaps_dataset-3.0.0.dist-info/RECORD
