Metadata-Version: 2.1
Name: gaps-dataset
Version: 3.0.0
Summary: Download script for GAPs deep learning dataset from TU Ilmenau
Home-page: http://www.tu-ilmenau.de/neurob/data-sets-code/gaps/
Author: Markus Eisenbach
Author-email: markus.eisenbach@tu-ilmenau.de
License: Copyright 2017, Neuroinformatics and Cognitive Robotics Lab TU Ilmenau, Ilmenau, Germany (for academic use only)
Platform: UNKNOWN
Requires-Dist: numpy
Provides-Extra: test
Requires-Dist: pytest (>=3.0.2) ; extra == 'test'
